ttd_workflows/__init__.py
ttd_workflows/_hooks/__init__.py
ttd_workflows/_hooks/registration.py
ttd_workflows/_hooks/sdkhooks.py
ttd_workflows/_hooks/types.py
ttd_workflows/_version.py
ttd_workflows/ad_group.py
ttd_workflows/adgroups.py
ttd_workflows/basesdk.py
ttd_workflows/campaign.py
ttd_workflows/campaigns.py
ttd_workflows/dmp.py
ttd_workflows/graphql_request.py
ttd_workflows/httpclient.py
ttd_workflows/job_status.py
ttd_workflows/models/__init__.py
ttd_workflows/models/adgroupassociatebidlist.py
ttd_workflows/models/adgroupaudiencetargeting.py
ttd_workflows/models/adgroupbudget.py
ttd_workflows/models/adgroupbulkcreateworkflowinputwithvalidation.py
ttd_workflows/models/adgroupbulkupdateworkflowinputwithvalidation.py
ttd_workflows/models/adgroupchannel.py
ttd_workflows/models/adgroupcomscoresettings.py
ttd_workflows/models/adgroupcontracttargeting.py
ttd_workflows/models/adgroupcreateworkflowinput.py
ttd_workflows/models/adgroupcreateworkflowinputwithvalidation.py
ttd_workflows/models/adgroupcreateworkflowprimaryinput.py
ttd_workflows/models/adgroupflight.py
ttd_workflows/models/adgroupfunnellocation.py
ttd_workflows/models/adgroupkoaoptimizationsettings.py
ttd_workflows/models/adgroupnielsentrackingattributes.py
ttd_workflows/models/adgrouppayload.py
ttd_workflows/models/adgrouproigoal.py
ttd_workflows/models/adgroupupdateworkflowinput.py
ttd_workflows/models/adgroupupdateworkflowinputwithvalidation.py
ttd_workflows/models/adgroupupdateworkflowprimaryinput.py
ttd_workflows/models/adgroupworkflow.py
ttd_workflows/models/adgroupworkflowadvancedinput.py
ttd_workflows/models/adgroupworkflowassociatebidlistinput.py
ttd_workflows/models/adgroupworkflowaudiencetargetinginput.py
ttd_workflows/models/adgroupworkflowbudgetinput.py
ttd_workflows/models/adgroupworkflowcomscoresettingsinput.py
ttd_workflows/models/adgroupworkflowcontracttargetinginput.py
ttd_workflows/models/adgroupworkflowflightinput.py
ttd_workflows/models/adgroupworkflowkoaoptimizationsettingsinput.py
ttd_workflows-0.11.0.dist-info/METADATA
ttd_workflows-0.11.0.dist-info/WHEEL
ttd_workflows-0.11.0.dist-info/RECORD
