Metadata-Version: 2.4
Name: ttd-workflows
Version: 0.11.0
Summary: Python Client SDK Generated by Speakeasy.
License: map[name:The MIT License (MIT) shortName:MIT url:https://mit-license.org/]
Author: Speakeasy
Requires-Python: >=3.9.2
Classifier: License :: Other/Proprietary License
Classifier: Programming Language :: Python :: 3
Classifier: Programming Language :: Python :: 3.10
Classifier: Programming Language :: Python :: 3.11
Classifier: Programming Language :: Python :: 3.12
Classifier: Programming Language :: Python :: 3.13
Classifier: Programming Language :: Python :: 3.14
Requires-Dist: httpcore (>=1.0.9)
Requires-Dist: httpx (>=0.28.1)
Requires-Dist: pydantic (>=2.11.2)
Project-URL: Repository, https://github.com/thetradedesk/ttd-workflows-python.git
